biomedlm/__init__.py
biomedlm-0.0.1.dev0.dist-info/METADATA
biomedlm-0.0.1.dev0.dist-info/WHEEL
biomedlm-0.0.1.dev0.dist-info/top_level.txt
biomedlm-0.0.1.dev0.dist-info/RECORD
