Metadata-Version: 2.1
Name: biomedlm
Version: 0.0.1.dev0
Summary: BioMedLM - Finetune LLM For Medical/Health
Home-page: UNKNOWN
Author: Juncong Moo
License: UNKNOWN
Keywords: BioMedLM
Platform: UNKNOWN
Classifier: Programming Language :: Python :: 3
Classifier: Programming Language :: Python :: 3.8
Classifier: Programming Language :: Python :: 3.9
Classifier: Programming Language :: Python :: 3.10
Requires-Dist: pyllama
